LICENSE
MANIFEST.in
README.rst
setup.cfg
setup.py
OGRe.egg-info/PKG-INFO
OGRe.egg-info/SOURCES.txt
OGRe.egg-info/dependency_links.txt
OGRe.egg-info/entry_points.txt
OGRe.egg-info/pbr.json
OGRe.egg-info/requires.txt
OGRe.egg-info/top_level.txt
ogre/Twitter.py
ogre/__init__.py
ogre/__main__.py
ogre/api.py
ogre/exceptions.py
ogre/validation.py
ogre/test/__init__.py
ogre/test/test_Twitter.py
ogre/test/test_api.py
ogre/test/test_twitter.py
ogre/test/test_validation.py
ogre/test/data/Twitter-response-example.json
snowflake2time/__init__.py
snowflake2time/snowflake.py
snowflake2time/test/__init__.py
snowflake2time/test/test_snowflake.py