Metadata-Version: 1.1
Name: OGRe
Version: 4.6.0
Summary: OpenFusion GeoJSON Retriever
Home-page: https://github.com/dmtucker/ogre
Author: David Tucker
Author-email: dmtucker@ucsc.edu
License: LGPLv2+
Keywords: OpenFusion Twitter GeoJSON geotag
Platform: UNKNOWN
Classifier: License :: OSI Approved :: GNU Lesser General Public License v2 or later (LGPLv2+)
Classifier: Intended Audience :: Developers
Classifier: Programming Language :: Python :: 2
Classifier: Programming Language :: Python :: 2.7
Classifier: Programming Language :: Python :: 3
Classifier: Programming Language :: Python :: 3.3
Classifier: Programming Language :: Python :: 3.4
Classifier: Programming Language :: Python :: 3.5
Classifier: Development Status :: 4 - Beta
